awsp/__init__.py
awsp/__main__.py
awsp/cli.py
awsp/config/__init__.py
awsp/config/models.py
awsp/config/parser.py
awsp/profiles/__init__.py
awsp/profiles/manager.py
awsp/shell/__init__.py
awsp/shell/hooks.py
awsp/ui/__init__.py
awsp/ui/display.py
awsp/ui/prompts.py
awsp-0.5.0.dist-info/METADATA
awsp-0.5.0.dist-info/WHEEL
awsp-0.5.0.dist-info/entry_points.txt
awsp-0.5.0.dist-info/RECORD
