Metadata-Version: 2.4
Name: awsp
Version: 0.5.0
Summary: AWS Profile Switcher - Manage AWS CLI profiles easily
Author: Punit
License: MIT
Keywords: aws,cli,iam,profile,sso,switcher
Classifier: Development Status :: 4 - Beta
Classifier: Environment :: Console
Classifier: Intended Audience :: Developers
Classifier: Intended Audience :: System Administrators
Classifier: License :: OSI Approved :: MIT License
Classifier: Operating System :: OS Independent
Classifier: Programming Language :: Python :: 3
Classifier: Programming Language :: Python :: 3.10
Classifier: Programming Language :: Python :: 3.11
Classifier: Programming Language :: Python :: 3.12
Classifier: Programming Language :: Python :: 3.13
Classifier: Topic :: Utilities
Requires-Python: >=3.10
Requires-Dist: questionary>=2.0.0
Requires-Dist: typer[all]>=0.9.0
Provides-Extra: dev
Requires-Dist: pytest-cov>=4.0.0; extra == 'dev'
Requires-Dist: pytest>=7.0.0; extra == 'dev'
